pydata_master/__init__.py
pydata_master/ads_platform.py
pydata_master/crm_system.py
pydata_master/database_connect.py
pydata_master/google_service.py
pydata_master/measurement_platform.py
pydata_master/messaging_api.py
pydata_master/visualization.py
pydata_master-0.0.7.dist-info/LICENSE
pydata_master-0.0.7.dist-info/METADATA
pydata_master-0.0.7.dist-info/WHEEL
pydata_master-0.0.7.dist-info/top_level.txt
pydata_master-0.0.7.dist-info/RECORD
