Metadata-Version: 2.1
Name: pydata-master
Version: 0.0.7
Summary: All frequently used functions in one package for the data operation in a daily basis.
Home-page: https://github.com/thinh-vu/pydata_master
Author: Thinh Vu
Author-email: mrthinh@live.com
Classifier: Programming Language :: Python :: 3
Classifier: License :: OSI Approved :: MIT License
Classifier: Operating System :: OS Independent
Requires-Python: >=3.7
License-File: LICENSE
Requires-Dist: df2gspread
Requires-Dist: nltk
Requires-Dist: google-auth-httplib2
Requires-Dist: ur-gadget
